infraboxcli/__init__.py
infraboxcli/console.py
infraboxcli/env.py
infraboxcli/execute.py
infraboxcli/graph.py
infraboxcli/init.py
infraboxcli/install.py
infraboxcli/job_list.py
infraboxcli/list_jobs.py
infraboxcli/log.py
infraboxcli/pull.py
infraboxcli/push.py
infraboxcli/run.py
infraboxcli/validate.py
infraboxcli/workflow.py
infraboxcli/dashboard/__init__.py
infraboxcli/dashboard/cli_client.py
infraboxcli/dashboard/external.py
infraboxcli/dashboard/local_config.py
infraboxcli/dashboard/project.py
infraboxcli/dashboard/remotes.py
infraboxcli/dashboard/user.py
infraboxcli-0.9.0.data/scripts/infrabox
pyinfrabox/__init__.py
pyinfrabox/test.py
pyinfrabox/utils.py
pyinfrabox/badge/__init__.py
pyinfrabox/docker_compose/__init__.py
pyinfrabox/infrabox/__init__.py
pyinfrabox/markup/__init__.py
pyinfrabox/testresult/__init__.py
infraboxcli-0.9.0.dist-info/METADATA
infraboxcli-0.9.0.dist-info/WHEEL
infraboxcli-0.9.0.dist-info/top_level.txt
infraboxcli-0.9.0.dist-info/RECORD
