Metadata-Version: 2.1
Name: infraboxcli
Version: 0.9.0
Summary: Command Line Interface for InfraBox
Home-page: https://github.com/infrabox/cli
Author: infrabox
License: MIT
Platform: UNKNOWN
Classifier: Development Status :: 4 - Beta
Classifier: Intended Audience :: Developers
Classifier: Topic :: Software Development :: Build Tools
Classifier: License :: OSI Approved :: Apache Software License
Classifier: Programming Language :: Python :: 2
Classifier: Programming Language :: Python :: 2.7
Classifier: Programming Language :: Python :: 3
Classifier: Programming Language :: Python :: 3.5
Classifier: Programming Language :: Python :: 3.6
Requires-Dist: future
Requires-Dist: jsonschema (==2.6.0)
Requires-Dist: requests
Requires-Dist: colorama
Requires-Dist: socketIO-client
Requires-Dist: PyJWT
Requires-Dist: cryptography
Requires-Dist: inquirer
Requires-Dist: pyyaml
